uncoverit/__init__.py
uncoverit/classes.py
uncoverit/exceptions.py
uncoverit/main.py
uncoverit-0.1.1.dist-info/METADATA
uncoverit-0.1.1.dist-info/WHEEL
uncoverit-0.1.1.dist-info/RECORD
