Metadata-Version: 2.4
Name: uncoverit
Version: 0.1.1
Summary: Async API client for uncoverit.org
Project-URL: Homepage, https://uncoverit.org
Project-URL: Repository, https://github.com/Uncover-it/uncoverit-packages
Project-URL: Tracker Issues, https://github.com/Uncover-it/uncoverit-packages/issues
Author-email: 144 <144@uncoverit.org>
Keywords: analysis,api,async,file,uncoverit,websocket
Classifier: Operating System :: OS Independent
Classifier: Programming Language :: Python :: 3
Classifier: Programming Language :: Python :: 3.9
Classifier: Programming Language :: Python :: 3.10
Classifier: Programming Language :: Python :: 3.11
Classifier: Programming Language :: Python :: 3.12
Classifier: Topic :: Security
Requires-Python: >=3.9
Requires-Dist: aiofiles>=23.2.0
Requires-Dist: aiohttp>=3.9.0
Requires-Dist: pefile>=2023.2.7
Requires-Dist: pydantic>=2.5.0
Requires-Dist: websockets>=12.0
